shit_env/__init__.py
shit_env-0.1.1.dist-info/METADATA
shit_env-0.1.1.dist-info/WHEEL
shit_env-0.1.1.dist-info/top_level.txt
shit_env-0.1.1.dist-info/RECORD
