Metadata-Version: 2.4
Name: shit-env
Version: 0.1.1
Summary: A simple .env file manager for Python, inspired by NodeJS dotenv
Author: AlexTheMueller
Author-email: alexalexandramueller@gmx.de
Classifier: Programming Language :: Python :: 3
Classifier: License :: OSI Approved :: MIT License
Classifier: Operating System :: OS Independent
Requires-Python: >=3.6
Dynamic: author
Dynamic: author-email
Dynamic: classifier
Dynamic: description
Dynamic: description-content-type
Dynamic: requires-python
Dynamic: summary
